pzem/__init__.py
pzem/pzem.py
python_pzem-0.1.5.dist-info/LICENSE
python_pzem-0.1.5.dist-info/METADATA
python_pzem-0.1.5.dist-info/WHEEL
python_pzem-0.1.5.dist-info/top_level.txt
python_pzem-0.1.5.dist-info/RECORD
