Metadata-Version: 2.1
Name: python-pzem
Version: 0.1.5
Summary: Python interface for PZEM-014 and PZEM-016 Energy Meters
Home-page: https://github.com/leandrotoledo/python-pzem
Author: Leandro Muto, Leandro Toledo
Author-email: leandro.muto@gmail.com, leandrotoledodesouza@gmail.com
License: LGPLv3
Project-URL: Bug Tracker, https://github.com/leandrotoledo/python-pzem/issues
Classifier: Development Status :: 5 - Production/Stable
Classifier: Intended Audience :: Developers
Classifier: License :: OSI Approved :: GNU Lesser General Public License v3 (LGPLv3)
Classifier: Operating System :: OS Independent
Classifier: Programming Language :: Python :: 3
Classifier: Topic :: Software Development :: Libraries :: Python Modules
Requires-Python: >=3.6
License-File: LICENSE
Requires-Dist: minimalmodbus
